moedaparatexto/__init__.py
moedaparatexto-0.1.dist-info/METADATA
moedaparatexto-0.1.dist-info/WHEEL
moedaparatexto-0.1.dist-info/top_level.txt
moedaparatexto-0.1.dist-info/RECORD
