Metadata-Version: 2.1
Name: moedaparatexto
Version: 0.1
Summary: Escrivao de valores de moeda por extenso
Home-page: http://github.com/rpsjr/moedaparatexto
Author: Raimundo Pereira da Silva Junior
Author-email: raimundopsjr@gmail.com
License: MIT
Platform: UNKNOWN
